osmiter/__init__.py
osmiter/parser_pbf.py
osmiter/parser_xml.py
osmiter/py.typed
osmiter/pbf/__init__.py
osmiter/pbf/fileformat_pb2.py
osmiter/pbf/osmformat_pb2.py
osmiter-1.3.1.data/data/README.md
osmiter-1.3.1.data/data/license.md
osmiter-1.3.1.dist-info/METADATA
osmiter-1.3.1.dist-info/WHEEL
osmiter-1.3.1.dist-info/top_level.txt
osmiter-1.3.1.dist-info/RECORD
