Metadata-Version: 2.1
Name: osmiter
Version: 1.3.1
Summary: Library for reading OSM XML/GZ/BZ2/PBF files
Home-page: https://github.com/MKuranowski/osmiter
Author: Mikołaj Kuranowski
License: MIT
Keywords: osm xml gz pz2 pbf openstreetmap parser
Classifier: Development Status :: 4 - Beta
Classifier: License :: OSI Approved :: MIT License
Classifier: Operating System :: OS Independent
Classifier: Programming Language :: Python :: 3 :: Only
Classifier: Topic :: Scientific/Engineering :: GIS
Classifier: Topic :: Software Development :: Libraries :: Python Modules
Requires-Python: >=3.6, <4
